odoo/addons/crm_rest_api/CHANGELOG.md
odoo/addons/crm_rest_api/README.rst
odoo/addons/crm_rest_api/__init__.py
odoo/addons/crm_rest_api/__manifest__.py
odoo/addons/crm_rest_api/services/__init__.py
odoo/addons/crm_rest_api/services/crm_lead_services.py
odoo/addons/crm_rest_api/services/schemas.py
odoo_addon_crm_rest_api-16.0.0.1.0.dist-info/METADATA
odoo_addon_crm_rest_api-16.0.0.1.0.dist-info/WHEEL
odoo_addon_crm_rest_api-16.0.0.1.0.dist-info/top_level.txt
odoo_addon_crm_rest_api-16.0.0.1.0.dist-info/RECORD
