Metadata-Version: 2.1
Name: odoo-addon-crm-rest-api
Version: 16.0.0.1.0
Summary: Expose CRM Lead on the Rest API
Home-page: 
Author: Coopdevs Treball SCCL
Classifier: Programming Language :: Python
Classifier: Framework :: Odoo
Classifier: Framework :: Odoo :: 16.0
Requires-Python: >=3.10
Requires-Dist: odoo-addon-base-rest <16.1dev,>=16.0dev
Requires-Dist: odoo-addon-component <16.1dev,>=16.0dev
Requires-Dist: odoo <16.1dev,>=16.0a
